{
	"configurations" : 
	[
		{
			"directories" : 
			[
				{
					"build" : ".",
					"hasInstallRule" : true,
					"jsonFile" : "directory-.-Release-f23b49df985d2c96756b.json",
					"minimumCMakeVersion" : 
					{
						"string" : "3.12"
					},
					"projectIndex" : 0,
					"source" : ".",
					"targetIndexes" : 
					[
						0,
						1,
						2
					]
				}
			],
			"name" : "Release",
			"projects" : 
			[
				{
					"directoryIndexes" : 
					[
						0
					],
					"name" : "pointcloud_adapter",
					"targetIndexes" : 
					[
						0,
						1,
						2
					]
				}
			],
			"targets" : 
			[
				{
					"directoryIndex" : 0,
					"id" : "adapter_node::@6890427a1f51a3e7e1df",
					"jsonFile" : "target-adapter_node-Release-cfda19fef5a52e7c49ce.json",
					"name" : "adapter_node",
					"projectIndex" : 0
				},
				{
					"directoryIndex" : 0,
					"id" : "pointcloud_adapter_uninstall::@6890427a1f51a3e7e1df",
					"jsonFile" : "target-pointcloud_adapter_uninstall-Release-d8c595e3b36fe128b567.json",
					"name" : "pointcloud_adapter_uninstall",
					"projectIndex" : 0
				},
				{
					"directoryIndex" : 0,
					"id" : "uninstall::@6890427a1f51a3e7e1df",
					"jsonFile" : "target-uninstall-Release-ef13f3fabfdba74bc76f.json",
					"name" : "uninstall",
					"projectIndex" : 0
				}
			]
		}
	],
	"kind" : "codemodel",
	"paths" : 
	{
		"build" : "/home/wook/ros2/ros2_ws/build/pointcloud_adapter",
		"source" : "/home/wook/ros2/ros2_ws/src/autonomy_stack_diablo_setup/src/slam/pointcloud_adapter"
	},
	"version" : 
	{
		"major" : 2,
		"minor" : 3
	}
}
