{
	"configurations" : 
	[
		{
			"directories" : 
			[
				{
					"build" : ".",
					"hasInstallRule" : true,
					"jsonFile" : "directory-.-Release-c1f5dfca4b15aff70718.json",
					"minimumCMakeVersion" : 
					{
						"string" : "3.12"
					},
					"projectIndex" : 0,
					"source" : ".",
					"targetIndexes" : 
					[
						0,
						1,
						2
					]
				}
			],
			"name" : "Release",
			"projects" : 
			[
				{
					"directoryIndexes" : 
					[
						0
					],
					"name" : "diablo_body",
					"targetIndexes" : 
					[
						0,
						1,
						2
					]
				}
			],
			"targets" : 
			[
				{
					"directoryIndex" : 0,
					"id" : "diablo_body_core::@6890427a1f51a3e7e1df",
					"jsonFile" : "target-diablo_body_core-Release-a1f02a46e00e5767b417.json",
					"name" : "diablo_body_core",
					"projectIndex" : 0
				},
				{
					"directoryIndex" : 0,
					"id" : "diablo_body_uninstall::@6890427a1f51a3e7e1df",
					"jsonFile" : "target-diablo_body_uninstall-Release-2aa3d77fc6f457cef238.json",
					"name" : "diablo_body_uninstall",
					"projectIndex" : 0
				},
				{
					"directoryIndex" : 0,
					"id" : "uninstall::@6890427a1f51a3e7e1df",
					"jsonFile" : "target-uninstall-Release-1dc9dea2fca6f9dea476.json",
					"name" : "uninstall",
					"projectIndex" : 0
				}
			]
		}
	],
	"kind" : "codemodel",
	"paths" : 
	{
		"build" : "/home/wook/ros2/ros2_ws/build/diablo_body",
		"source" : "/home/wook/ros2/ros2_ws/src/autonomy_stack_diablo_setup/src/utilities/diablo_ros2/diablo_ception/diablo_body"
	},
	"version" : 
	{
		"major" : 2,
		"minor" : 3
	}
}
